src/__init__.py
src/main.py
bigDataSML-0.1.3.dist-info/METADATA
bigDataSML-0.1.3.dist-info/WHEEL
bigDataSML-0.1.3.dist-info/top_level.txt
bigDataSML-0.1.3.dist-info/RECORD
