Metadata-Version: 2.1
Name: bigDataSML
Version: 0.1.3
Summary: This package calculates average student performances
Home-page: https://github.com/Samu2021/bigDataSML
Author: SML (Samuel Schlenker)
Author-email: wi20067@lehre.dhbw-stuttgart.de
License: UNKNOWN
Keywords: python,spark,pyspark,student,performance,calculation,bigdata,programming,fun,sml
Platform: UNKNOWN
Classifier: Development Status :: 4 - Beta
Classifier: Intended Audience :: Education
Classifier: Programming Language :: Python :: 2.7
Classifier: Natural Language :: English
Classifier: Natural Language :: German
Classifier: Operating System :: Unix
Classifier: Operating System :: MacOS :: MacOS X
Classifier: Operating System :: Microsoft :: Windows
Requires-Dist: pyspark (>=2.3.0)
